Workbook

Sheet README
A1: Retail Sales Planning & Analytics Toolkit
A3: Data source: UCI "Online Retail" dataset - real UK-based online gift retailer,
A4: 01/12/2010 to 09/12/2011. 528,962 real transactions across 38 countries and 4,073 products.
A5: Public dataset (CC BY 4.0). Chen, D. (2015). Online Retail. UCI Machine Learning Repository.
A7: Project structure:
A8: 1. Monthly Sales (Wide) - raw monthly report, top 10 products x 13 months, as received
A9: 2. Monthly Sales (Long) - unpivoted via Power Query (Unpivot Other Columns), then
A10: auto-formatted via VBA macro (see FormatMonthlySalesReport.bas)
A11: 3. Loan Details / Amortization - inventory financing model (PMT/IPMT/PPMT) sized against
A12: this product's real average monthly revenue
A13: 4. Production Mix (Solver) - profit-maximizing stock order under budget & storage constraints,
A14: using real average unit prices; margin assumption documented on sheet
... A24: - Loan model assumes a standalone 12-month inventory financing facility at 7.5% APR

Sheet Monthly Sales (Wide)
A1: Product | B1: Dec-10 | C1: Jan-11 | D1: Feb-11 | E1: Mar-11 | F1: Apr-11 | G1: May-11 | H1: Jun-11 | I1: Jul-11 | J1: Aug-11 | K1: Sep-11 | L1: Oct-11 | M1: Nov-11 | N1: Dec-11
A2: ASSORTED COLOUR BIRD ORNAMENT | B2: 3986 | C2: 2921 | D2: 2736 | E2: 4303 | F2: 4174 | G2: 5052 | H2: 2628 | I2: 3129 | J2: 9882 | K2: 4994 | L2: 4686 | M2: 8441 | N2: 2163
A3: CHILLI LIGHTS | B3: 7506 | C3: 5901 | D3: 3616 | E3: 3093 | F3: 358 | G3: 2297 | H3: 2310 | I3: 4295 | J3: 2260 | K3: 3677 | L3: 4678 | M3: 11486 | N3: 2640
A4: JUMBO BAG RED RETROSPOT | B4: 4019 | C4: 5048 | D4: 5617 | E4: 10118 | F4: 4878 | G4: 7123 | H4: 7248 | I4: 6254 | J4: 10797 | K4: 8884 | L4: 10486 | M4: 11641 | N4: 2227
A5: MEDIUM CERAMIC TOP STORAGE JAR | B5: 0 | C5: 77184 | D5: 0 | E5: 0 | F5: 0 | G5: 891 | H5: 473 | I5: 858 | J5: 540 | K5: 407 | L5: 321 | M5: 775 | N5: 253
A6: PAPER CHAIN KIT 50'S CHRISTMAS | B6: 9226 | C6: 143 | D6: 25 | E6: 232 | F6: 44 | G6: 65 | H6: 911 | I6: 1078 | J6: 1335 | K6: 6006 | L6: 10031 | M6: 28985 | N6: 6871
A7: PAPER CRAFT , LITTLE BIRDIE | B7: 0 | C7: 0 | D7: 0 | E7: 0 | F7: 0 | G7: 0 | H7: 0 | I7: 0 | J7: 0 | K7: 0 | L7: 0 | M7: 0 | N7: 168470
A8: PARTY BUNTING | B8: 1208 | C8: 2288 | D8: 4348 | E8: 9123 | F8: 10778 | G8: 19148 | H8: 12561 | I8: 14576 | J8: 9695 | K8: 6403 | L8: 3716 | M8: 4741 | N8: 918
A9: RABBIT NIGHT LIGHT | B9: 0 | C9: 0 | D9: 0 | E9: 0 | F9: 0 | G9: 2280 | H9: 3327 | I9: 669 | J9: 3534 | K9: 700 | L9: 12257 | M9: 34557 | N9: 9643
A10: REGENCY CAKESTAND 3 TIER | B10: 27870 | C10: 12801 | D10: 11009 | E10: 18372 | F10: 14813 | G10: 12646 | H10: 9745 | I10: 13987 | J10: 10534 | K10: 9620 | L10: 13281 | M10: 13800 | N10: 6007
A11: WHITE HANGING HEART T-LIGHT HOLDER | B11: 11234 | C11: 15276 | D11: 5140 | E11: 5598 | F11: 10018 | G11: 11415 | H11: 4707 | I11: 8630 | J11: 5733 | K11: 7123 | L11: 4848 | M11: 14362 | N11: 2207

Sheet Monthly Sales (Long)
A1: Product | B1: Month | C1: Revenue
A2: ASSORTED COLOUR BIRD ORNAMENT | B2: Dec-10 | C2: 3986
A3: ASSORTED COLOUR BIRD ORNAMENT | B3: Jan-11 | C3: 2921
A4: ASSORTED COLOUR BIRD ORNAMENT | B4: Feb-11 | C4: 2736
A5: ASSORTED COLOUR BIRD ORNAMENT | B5: Mar-11 | C5: 4303
A6: ASSORTED COLOUR BIRD ORNAMENT | B6: Apr-11 | C6: 4174
A7: ASSORTED COLOUR BIRD ORNAMENT | B7: May-11 | C7: 5052
A8: ASSORTED COLOUR BIRD ORNAMENT | B8: Jun-11 | C8: 2628
A9: ASSORTED COLOUR BIRD ORNAMENT | B9: Jul-11 | C9: 3129
A10: ASSORTED COLOUR BIRD ORNAMENT | B10: Aug-11 | C10: 9882
A11: ASSORTED COLOUR BIRD ORNAMENT | B11: Sep-11 | C11: 4994
A12: ASSORTED COLOUR BIRD ORNAMENT | B12: Oct-11 | C12: 4686
A13: ASSORTED COLOUR BIRD ORNAMENT | B13: Nov-11 | C13: 8441
... A110: WHITE HANGING HEART T-LIGHT HOLDER | B110: Dec-11 | C110: 2207
A111: Total | C111: =SUM(C2:C110) -> 969922
A113: Built by: Power Query 'Unpivot Other Columns' on Monthly Sales (Wide), then FormatMonthlySalesReport VBA macro (bold header, currency format, dynamic Total row via LastRow, borders). See FormatMonthlySalesReport.bas.

Sheet Loan Details
A1: Inventory Financing - Loan Details
A3: Loan Amount (Principal) | B3: 25000
A4: Annual Interest Rate | B4: 0.075
A5: Loan Term (Years) | B5: 1
A6: Payments per Year | B6: 12
A9: Business case: REGENCY CAKESTAND 3 TIER is the top real product by revenue (£174,485 total). Average monthly revenue for this product is ~£13,400, peaking at £27,870 in December. £25,000 (~2x average monthly revenue) sized to fund inventory buildup ahead of the Nov/Dec peak.

Sheet Amortization
A1: Inventory Loan Amortization Schedule
A3: Monthly Payment: | B3: =-PMT('Loan Details'!$B$4/'Loan Details'!$B$6,'Loan Details'!$B$5*'Loan Details'!$B$6,'Loan Details'!$B$3) -> 2168.9354
A6: Month | B6: Payment | C6: Interest | D6: Principal | E6: Remaining Balance
A7: 1 | B7: =$B$3 -> 2168.9354 | C7: =-IPMT('Loan Details'!$B$4/'Loan Details'!$B$6,A7,'Loan Details'!$B$5*'Loan Details'!$B$6,'Loan Details'!$B$3) -> 156.25 | D7: =-PPMT('Loan Details'!$B$4/'Loan Details'!$B$6,A7,'Loan Details'!$B$5*'Loan Details'!$B$6,'Loan Details'!$B$3) -> 2012.6854 | E7: ='Loan Details'!$B$3-D7 -> 22987.315
A8: 2 | B8: =$B$3 -> 2168.9354 | C8: =-IPMT('Loan Details'!$B$4/'Loan Details'!$B$6,A8,'Loan Details'!$B$5*'Loan Details'!$B$6,'Loan Details'!$B$3) -> 143.67072 | D8: =-PPMT('Loan Details'!$B$4/'Loan Details'!$B$6,A8,'Loan Details'!$B$5*'Loan Details'!$B$6,'Loan Details'!$B$3) -> 2025.2647 | E8: =E7-D8 -> 20962.05
A9: 3 | B9: =$B$3 -> 2168.9354 | C9: =-IPMT('Loan Details'!$B$4/'Loan Details'!$B$6,A9,'Loan Details'!$B$5*'Loan Details'!$B$6,'Loan Details'!$B$3) -> 131.01281 | D9: =-PPMT('Loan Details'!$B$4/'Loan Details'!$B$6,A9,'Loan Details'!$B$5*'Loan Details'!$B$6,'Loan Details'!$B$3) -> 2037.9226 | E9: =E8-D9 -> 18924.127
A10: 4 | B10: =$B$3 -> 2168.9354 | C10: =-IPMT('Loan Details'!$B$4/'Loan Details'!$B$6,A10,'Loan Details'!$B$5*'Loan Details'!$B$6,'Loan Details'!$B$3) -> 118.2758 | D10: =-PPMT('Loan Details'!$B$4/'Loan Details'!$B$6,A10,'Loan Details'!$B$5*'Loan Details'!$B$6,'Loan Details'!$B$3) -> 2050.6596 | E10: =E9-D10 -> 16873.468
A11: 5 | B11: =$B$3 -> 2168.9354 | C11: =-IPMT('Loan Details'!$B$4/'Loan Details'!$B$6,A11,'Loan Details'!$B$5*'Loan Details'!$B$6,'Loan Details'!$B$3) -> 105.45917 | D11: =-PPMT('Loan Details'!$B$4/'Loan Details'!$B$6,A11,'Loan Details'!$B$5*'Loan Details'!$B$6,'Loan Details'!$B$3) -> 2063.4762 | E11: =E10-D11 -> 14809.991
A12: 6 | B12: =$B$3 -> 2168.9354 | C12: =-IPMT('Loan Details'!$B$4/'Loan Details'!$B$6,A12,'Loan Details'!$B$5*'Loan Details'!$B$6,'Loan Details'!$B$3) -> 92.562446 | D12: =-PPMT('Loan Details'!$B$4/'Loan Details'!$B$6,A12,'Loan Details'!$B$5*'Loan Details'!$B$6,'Loan Details'!$B$3) -> 2076.373 | E12: =E11-D12 -> 12733.618
A13: 7 | B13: =$B$3 -> 2168.9354 | C13: =-IPMT('Loan Details'!$B$4/'Loan Details'!$B$6,A13,'Loan Details'!$B$5*'Loan Details'!$B$6,'Loan Details'!$B$3) -> 79.585115 | D13: =-PPMT('Loan Details'!$B$4/'Loan Details'!$B$6,A13,'Loan Details'!$B$5*'Loan Details'!$B$6,'Loan Details'!$B$3) -> 2089.3503 | E13: =E12-D13 -> 10644.268
A14: 8 | B14: =$B$3 -> 2168.9354 | C14: =-IPMT('Loan Details'!$B$4/'Loan Details'!$B$6,A14,'Loan Details'!$B$5*'Loan Details'!$B$6,'Loan Details'!$B$3) -> 66.526676 | D14: =-PPMT('Loan Details'!$B$4/'Loan Details'!$B$6,A14,'Loan Details'!$B$5*'Loan Details'!$B$6,'Loan Details'!$B$3) -> 2102.4087 | E14: =E13-D14 -> 8541.8594
A15: 9 | B15: =$B$3 -> 2168.9354 | C15: =-IPMT('Loan Details'!$B$4/'Loan Details'!$B$6,A15,'Loan Details'!$B$5*'Loan Details'!$B$6,'Loan Details'!$B$3) -> 53.386621 | D15: =-PPMT('Loan Details'!$B$4/'Loan Details'!$B$6,A15,'Loan Details'!$B$5*'Loan Details'!$B$6,'Loan Details'!$B$3) -> 2115.5488 | E15: =E14-D15 -> 6426.3106
A16: 10 | B16: =$B$3 -> 2168.9354 | C16: =-IPMT('Loan Details'!$B$4/'Loan Details'!$B$6,A16,'Loan Details'!$B$5*'Loan Details'!$B$6,'Loan Details'!$B$3) -> 40.164441 | D16: =-PPMT('Loan Details'!$B$4/'Loan Details'!$B$6,A16,'Loan Details'!$B$5*'Loan Details'!$B$6,'Loan Details'!$B$3) -> 2128.771 | E16: =E15-D16 -> 4297.5396
A17: 11 | B17: =$B$3 -> 2168.9354 | C17: =-IPMT('Loan Details'!$B$4/'Loan Details'!$B$6,A17,'Loan Details'!$B$5*'Loan Details'!$B$6,'Loan Details'!$B$3) -> 26.859622 | D17: =-PPMT('Loan Details'!$B$4/'Loan Details'!$B$6,A17,'Loan Details'!$B$5*'Loan Details'!$B$6,'Loan Details'!$B$3) -> 2142.0758 | E17: =E16-D17 -> 2155.4638
A18: 12 | B18: =$B$3 -> 2168.9354 | C18: =-IPMT('Loan Details'!$B$4/'Loan Details'!$B$6,A18,'Loan Details'!$B$5*'Loan Details'!$B$6,'Loan Details'!$B$3) -> 13.471649 | D18: =-PPMT('Loan Details'!$B$4/'Loan Details'!$B$6,A18,'Loan Details'!$B$5*'Loan Details'!$B$6,'Loan Details'!$B$3) -> 2155.4638 | E18: =E17-D18 -> 0
A20: Total Interest Paid: | C20: =SUM(C7:C18) -> 1027.2251

Sheet Production Mix (Solver)
A1: Monthly Stock Order Optimization
A2: Real avg. unit prices from the dataset. Cost assumed at 60% of price (margin assumption - no cost data in source). Storage footprint (sqft/unit) is an estimated planning assumption.
A4: Cakestand units to order | B4: 0
A5: Jumbo Bag units to order | B5: 10080.645
B8: Unit Price | C8: Assumed Cost | D8: Profit/Unit | E8: Storage (sqft/unit)
A9: REGENCY CAKESTAND 3 TIER | B9: 13.96 | C9: =B9*0.6 -> 8.376 | D9: =B9-C9 -> 5.584 | E9: 0.4
A10: JUMBO BAG RED RETROSPOT | B10: 2.48 | C10: =B10*0.6 -> 1.488 | D10: =B10-C10 -> 0.992 | E10: 0.03
A12: Monthly Restocking Budget | B12: 15000
A13: Warehouse Storage Capacity (sqft) | B13: 350
A15: Total Profit | B15: =B4*D9+B5*D10 -> 10000
A16: Budget Used | B16: =B4*C9+B5*C10 -> 15000
A17: Storage Used | B17: =B4*E9+B5*E10 -> 302.41935
A19: Solver setup: Set Objective B15 (Max), By Changing B4:B5, Subject to: B16<=B12, B17<=B13, B4:B5>=0. Solving Method: Simplex LP. (Run Solver in Excel to populate B4:B5 - not executable from this environment.)
